dsa_utilities/__init__.py
dsa_utilities/timerfunc.py
py_dsa_utils/__init__.py
py_dsa_utils/timerfunc.py
py_dsa_utils-0.3.dist-info/METADATA
py_dsa_utils-0.3.dist-info/WHEEL
py_dsa_utils-0.3.dist-info/top_level.txt
py_dsa_utils-0.3.dist-info/RECORD
